wikitcms/__init__.py
wikitcms/event.py
wikitcms/exceptions.py
wikitcms/helpers.py
wikitcms/listing.py
wikitcms/page.py
wikitcms/release.py
wikitcms/result.py
wikitcms/wiki.py
wikitcms-2.6.21.dist-info/licenses/COPYING
wikitcms-2.6.21.dist-info/METADATA
wikitcms-2.6.21.dist-info/WHEEL
wikitcms-2.6.21.dist-info/top_level.txt
wikitcms-2.6.21.dist-info/RECORD
