Metadata-Version: 2.4
Name: wikitcms
Version: 2.6.21
Summary: Fedora QA wiki test management library
Home-page: https://pagure.io/fedora-qa/python-wikitcms
Author: Adam Williamson
Author-email: awilliam@redhat.com
License: GPLv3+
Keywords: fedora qa mediawiki validation
Classifier: Development Status :: 5 - Production/Stable
Classifier: Topic :: Utilities
Classifier: License :: OSI Approved :: GNU General Public License v3 or later (GPLv3+)
License-File: COPYING
Requires-Dist: cached-property
Requires-Dist: fedfind>=3.3.0
Requires-Dist: mwclient>=0.8.2
Requires-Dist: setuptools
Dynamic: author
Dynamic: author-email
Dynamic: classifier
Dynamic: description
Dynamic: description-content-type
Dynamic: home-page
Dynamic: keywords
Dynamic: license
Dynamic: license-file
Dynamic: requires-dist
Dynamic: summary
